lokrez/__init__.py
lokrez/__main__.py
lokrez/challonge.py
lokrez/export.py
lokrez/resources.py
lokrez/smashgg.py
lokrez/version.py
lokrez/data/playerskinsdb.json
lokrez/games/__init__.py
lokrez/games/melee.py
lokrez/games/pplus.py
lokrez/games/ssbu.py
lokrez/queries/getCharsByTournamentIdAndEntrantIds.gql
lokrez/queries/getTournamentEntrantsBySlug.gql
lokrez/queries/getTournamentTopById.gql
lokrez/queries/getTournamentTopBySlug.gql
lokrez/templates/_covid/banjo & kazooie.svg.j2
lokrez/templates/_covid/bayonetta.svg.j2
lokrez/templates/_covid/bowser jr.svg.j2
lokrez/templates/_covid/bowser.svg.j2
lokrez/templates/_covid/byleth f.svg.j2
lokrez/templates/_covid/byleth m.svg.j2
lokrez/templates/_covid/captain falcon.svg.j2
lokrez/templates/_covid/chrom.svg.j2
lokrez/templates/_covid/cloud.svg.j2
lokrez/templates/_covid/corrin f.svg.j2
lokrez/templates/_covid/corrin m.svg.j2
lokrez/templates/_covid/covid.j2
lokrez/templates/_covid/daisy.svg.j2
lokrez/templates/_covid/dark pit.svg.j2
lokrez/templates/_covid/dark samus.svg.j2
lokrez/templates/_covid/diddy kong.svg.j2
lokrez/templates/_covid/donkey kong.svg.j2
lokrez/templates/_covid/dr mario.svg.j2
lokrez/templates/_covid/falco.svg.j2
lokrez/templates/_covid/fox.svg.j2
lokrez/templates/_covid/ganondorf.svg.j2
lokrez/templates/_covid/greninja.svg.j2
lokrez/templates/_covid/hero.svg.j2
lokrez/templates/_covid/ice climbers.svg.j2
lokrez/templates/_covid/ike.svg.j2
lokrez/templates/_covid/incineroar.svg.j2
lokrez/templates/_covid/inkling.svg.j2
lokrez/templates/_covid/isabelle.svg.j2
lokrez/templates/_covid/jigglypuff.svg.j2
lokrez/templates/_covid/joker.svg.j2
lokrez/templates/_covid/ken.svg.j2
lokrez/templates/_covid/king dedede.svg.j2
lokrez/templates/_covid/king k rool.svg.j2
lokrez/templates/_covid/kirby.svg.j2
lokrez/templates/_covid/link.svg.j2
lokrez/templates/_covid/little mac.svg.j2
lokrez/templates/_covid/lucario.svg.j2
lokrez/templates/_covid/lucas.svg.j2
lokrez/templates/_covid/lucina.svg.j2
lokrez-4.3.0.dist-info/LICENSE
lokrez-4.3.0.dist-info/METADATA
lokrez-4.3.0.dist-info/WHEEL
lokrez-4.3.0.dist-info/entry_points.txt
lokrez-4.3.0.dist-info/top_level.txt
lokrez-4.3.0.dist-info/RECORD
