Metadata-Version: 2.1
Name: lokrez
Version: 4.3.0
Summary: Smash.gg-connected top8 graphics generator for Super Smash Bros Ultimate tournaments
Home-page: https://git.lertsenem.com/lertsenem/ssbu_lokrez
Author: Lertsenem
Author-email: lertsenem@lertsenem.com
License: MIT
Keywords: smash ultimate local results esport smashgg
Platform: UNKNOWN
Classifier: Programming Language :: Python :: 3
Classifier: License :: OSI Approved :: MIT License
Classifier: Operating System :: OS Independent
Classifier: Intended Audience :: End Users/Desktop
Classifier: Topic :: Multimedia :: Graphics
Classifier: Environment :: Console
Requires-Python: >=3.5
Requires-Dist: appdirs
Requires-Dist: jinja2
Requires-Dist: requests
